tomata/__init__.py
tomata/async_emitter.py
tomata/base.py
tomata/emitter.py
tomata/py.typed
tomata-1.1.0.dist-info/LICENSE
tomata-1.1.0.dist-info/METADATA
tomata-1.1.0.dist-info/WHEEL
tomata-1.1.0.dist-info/RECORD
