Metadata-Version: 2.1
Name: tomata
Version: 1.1.0
Summary: 
Home-page: https://github.com/evtn/tomata
License: MIT
Author: Dmitry Gritsenko
Author-email: tomata@evtn.me
Requires-Python: >=3.8,<4.0
Classifier: License :: OSI Approved :: MIT License
Classifier: Programming Language :: Python :: 3
Classifier: Programming Language :: Python :: 3.8
Classifier: Programming Language :: Python :: 3.9
Classifier: Programming Language :: Python :: 3.10
Classifier: Programming Language :: Python :: 3.11
Classifier: Programming Language :: Python :: 3.12
Project-URL: Repository, https://github.com/evtn/tomata
